Metadata-Version: 2.1
Name: ChatGskBot
Version: 2.0.0
Summary: Chatgpt GSK
Author-email: doneld528@gmail.com
